canary_sefi/__init__.py
canary_sefi/copyright.py
canary_sefi/task_manager.py
canary_sefi/compatibility_repair/__init__.py
canary_sefi/compatibility_repair/repair.py
canary_sefi/compatibility_repair/repair_v2_0_0.py
canary_sefi/compatibility_repair/repair_v2_0_3.py
canary_sefi/core/__init__.py
canary_sefi/core/component/__init__.py
canary_sefi/core/component/component_decorator.py
canary_sefi/core/component/component_dict.py
canary_sefi/core/component/component_enum.py
canary_sefi/core/component/component_exception.py
canary_sefi/core/component/component_manager.py
canary_sefi/core/component/default_component/__init__.py
canary_sefi/core/component/default_component/dataset_getter.py
canary_sefi/core/component/default_component/model_getter.py
canary_sefi/core/component/default_component/params_handler.py
canary_sefi/core/config/__init__.py
canary_sefi/core/config/config_manager.py
canary_sefi/core/function/__init__.py
canary_sefi/core/function/adversarial_training.py
canary_sefi/core/function/comparative_test_adv_example.py
canary_sefi/core/function/generate_adv_example.py
canary_sefi/core/function/inference.py
canary_sefi/core/function/init_dataset.py
canary_sefi/core/function/test_and_evaluation.py
canary_sefi/core/function/training_and_evaluation.py
canary_sefi/core/function/basic/__init__.py
canary_sefi/core/function/basic/attacker_function.py
canary_sefi/core/function/basic/img_trans_function.py
canary_sefi/core/function/basic/model_function.py
canary_sefi/core/function/basic/train_function.py
canary_sefi/core/function/basic/dataset/__init__.py
canary_sefi/core/function/basic/dataset/adv_dataset_function.py
canary_sefi/core/function/basic/dataset/dataset_function.py
canary_sefi/core/function/basic/dataset/memory_cache.py
canary_sefi/core/function/basic/dataset/tools.py
canary_sefi/core/function/enum/__init__.py
canary_sefi/core/function/enum/multi_db_mode_enum.py
canary_sefi/core/function/enum/step_enum.py
canary_sefi/core/function/enum/test_level_enum.py
canary_sefi-2.1.2.dist-info/LICENSE
canary_sefi-2.1.2.dist-info/METADATA
canary_sefi-2.1.2.dist-info/WHEEL
canary_sefi-2.1.2.dist-info/top_level.txt
canary_sefi-2.1.2.dist-info/RECORD
