Metadata-Version: 2.1
Name: canary-sefi
Version: 2.1.2
Summary: Canary SEFI is a framework for evaluating the adversarial robustness of deep learning-based image recognition models.
Home-page: https://github.com/NeoSunJZ/Canary_Master
Author: jiazheng.sun
Author-email: jiazheng.sun@foxmail.com
License: Apache
Classifier: License :: OSI Approved :: Apache Software License
Classifier: Natural Language :: English
Classifier: Operating System :: OS Independent
Classifier: Programming Language :: Python
Classifier: Programming Language :: Python :: 3.8
Classifier: Topic :: Software Development :: Libraries :: Python Modules
Requires-Python: >=3.8
License-File: LICENSE
Requires-Dist: torch >=2.0.1
Requires-Dist: torchvision >=0.16.1
Requires-Dist: colorama >=0.4.6
Requires-Dist: tqdm >=4.66.0
Requires-Dist: flask >=3.0.0
Requires-Dist: flask-socketio >=5.3.6
Requires-Dist: matplotlib >=3.7.4
Requires-Dist: opencv-python >=4.8.1.78
Requires-Dist: piq ==0.7.0
Requires-Dist: pandas >=2.0.3
Requires-Dist: seaborn >=0.13.0
Requires-Dist: scikit-learn >=1.3.2
